snz_movie_recsys/__init__.py
snz_movie_recsys/main.py
snz_movie_recsys-0.2.0.dist-info/METADATA
snz_movie_recsys-0.2.0.dist-info/WHEEL
snz_movie_recsys-0.2.0.dist-info/entry_points.txt
snz_movie_recsys-0.2.0.dist-info/top_level.txt
snz_movie_recsys-0.2.0.dist-info/RECORD
