Metadata-Version: 2.4
Name: snz-movie-recsys
Version: 0.2.0
Summary: A LangGraph-powered chatbot using tools like OpenAI
Author-email: Seungho Song <songseungho9258@gmail.com>
Project-URL: Homepage, https://github.com/Team-SNZ/snz-movie-recsys
Project-URL: Repository, https://github.com/Team-SNZ/snz-movie-recsys
Requires-Python: >=3.10
Requires-Dist: langchain
Requires-Dist: langgraph
Requires-Dist: langchain-openai
Requires-Dist: langchain-tavily
Requires-Dist: langchain-community
Requires-Dist: python-dotenv
Requires-Dist: pandas
Requires-Dist: faiss-cpu
